setup.py
pyaib/__init__.py
pyaib/channels.py
pyaib/components.py
pyaib/config.py
pyaib/db.py
pyaib/events.py
pyaib/irc.py
pyaib/ircbot.py
pyaib/linesocket.py
pyaib/nickserv.py
pyaib/plugins.py
pyaib/timers.py
pyaib/triggers.py
pyaib.egg-info/PKG-INFO
pyaib.egg-info/SOURCES.txt
pyaib.egg-info/dependency_links.txt
pyaib.egg-info/requires.txt
pyaib.egg-info/top_level.txt
pyaib/dbd/__init__.py
pyaib/dbd/sqlite.py
pyaib/util/__init__.py
pyaib/util/data.py
pyaib/util/decorator.py