Metadata-Version: 1.1
Name: pyaib
Version: 1.1.0
Summary: Python Framework for writing IRC Bots using gevent
Home-page: http://github.com/facebook/pyaib
Author: Jason Fried, Facebook
Author-email: fried@fb.com
License: Apache 2.0
Platform: UNKNOWN
Classifier: License :: OSI Approved :: Apache Software License
Classifier: Topic :: Communications :: Chat :: Internet Relay Chat
Classifier: Programming Language :: Python :: 2.7
Classifier: Intended Audience :: Developers
Classifier: Development Status :: 5 - Production/Stable
